{
	"black":        "#002b36",
	"dark_blue":    "#268bd2",
	"dark_green":   "#859900",
	"dark_cyan":    "#2aa198",
	"dark_red":     "#dc322f",
	"dark_magenta": "#d33682",
	"dark_yellow":  "#b58900",
	"gray":         "#eee8d5",
	"dark_gray":    "#073642",
	"blue":         "#839496",
	"green":        "#586e75",
	"cyan":         "#93a1a1",
	"red":          "#cb4b16",
	"magenta":      "#6c71c4",
	"yellow":       "#657b83",
	"white":        "#fdf6e3",

	"screen_colors": "blue,black",
	"popup_colors":  "yellow,white",
	
	"font_face":       "Consolas",
	"font_true_type":  true,
	"font_size":       "0x20",
	"font_weight":     700,

	"cursor_size": "small", 

	"window_size":        "80x25",
	"screen_buffer_size": "80x3000",

	"command_history_length": 200,
	"num_history_buffers":      4,

	"quick_edit":  true,
	"insert_mode": true,
	"fullscreen":  false,

	"load_console_IME":  true
}