{
    "black":        "#1e1e1e",
    "dark_blue":    "#323537",
    "dark_green":   "#464b50",
    "dark_cyan":    "#5f5a60",
    "dark_red":     "#838184",
    "dark_magenta": "#a7a7a7",
    "dark_yellow":  "#c3c3c3",
    "gray":         "#ffffff",
    "dark_gray":    "#cf6a4c",
    "blue":         "#cda869",
    "green":        "#f9ee98",
    "cyan":         "#8f9d6a",
    "red":          "#afc4db",
    "magenta":      "#7587a6",
    "yellow":       "#9b859d",
    "white":        "#9b703f",
    "screen_colors": "dark_magenta,black",
    "popup_colors":  "dark_red,dark_blue"
}
